[
  {
    "name": "ABC Money Exchange",
    "address": "2510 Otay Center Dr, San Diego, CA 92154",
    "phone": "(619) 690-0776"
  },
  {
    "name": "Baja-Mex Currency Services",
    "address": "320 Bolton Hall Rd, San Diego, CA 92173",
    "phone": "(619) 429-9400"
  },
  {
    "name": "Border X Change",
    "address": "1165 E Otay Mesa Blvd, San Diego, CA 92154",
    "phone": "(619) 281-0100"
  },
  {
    "name": "Baja-Mex",
    "address": "1177 E Otay Mesa Blvd, San Diego, CA 92154",
    "phone": "(619) 281-0111"
  },
  {
    "name": "Baja-Mex Insurance & Currency Exchange",
    "address": "2310 Roll Dr, San Diego, CA 92154",
    "phone": "(619) 661-6224"
  },
  {
    "name": "Casa de Cambio Alberto Padilla",
    "address": "1179 E Otay Mesa Blvd, San Diego, CA 92154",
    "phone": "(619) 690-0777"
  },
  {
    "name": "Casa de Cambio Tijuana",
    "address": "117 W San Ysidro Blvd, San Diego, CA 92154",
    "phone": "(619) 955-7210"
  },
  {
    "name": "Super Money Exchange",
    "address": "1159 E Otay Mesa Blvd, San Diego, CA 92154",
    "phone": "(619) 281-0111"
  },
  {
    "name": "Super Money Exchange",
    "address": "1201 Broadway, Chula Vista, CA 91910",
    "phone": "(619) 690-5035"
  }
]
